laebelmaker/__init__.py
laebelmaker/__main__.py
laebelmaker/cli.py
laebelmaker/datatypes.py
laebelmaker/errors.py
laebelmaker/label.py
laebelmaker/utils/__init__.py
laebelmaker/utils/formatter.py
laebelmaker/utils/input.py
laebelmaker/utils/loader.py
laebelmaker-0.4.1.dist-info/LICENSE
laebelmaker-0.4.1.dist-info/METADATA
laebelmaker-0.4.1.dist-info/WHEEL
laebelmaker-0.4.1.dist-info/entry_points.txt
laebelmaker-0.4.1.dist-info/top_level.txt
laebelmaker-0.4.1.dist-info/RECORD
