Metadata-Version: 2.1
Name: laebelmaker
Version: 0.4.1
Summary: Generate traefik labels easily
Author-email: Ivan Bratović <ivanbratovic4@gmail.com>
Project-URL: Homepage, https://github.com/ivanbratovic/laebelmaker
Keywords: traefik,label,generate
Classifier: Development Status :: 3 - Alpha
Classifier: Intended Audience :: System Administrators
Classifier: License :: OSI Approved :: MIT License
Classifier: Environment :: Console
Classifier: Programming Language :: Python
Classifier: Programming Language :: Python :: 3
Classifier: Programming Language :: Python :: 3.9
Classifier: Programming Language :: Python :: 3.10
Classifier: Programming Language :: Python :: 3.11
Classifier: Programming Language :: Python :: 3 :: Only
Classifier: Topic :: Internet
Classifier: Topic :: Utilities
Classifier: Topic :: System :: Systems Administration
Classifier: Operating System :: POSIX
Classifier: Operating System :: Unix
Classifier: Operating System :: MacOS
Requires-Python: >=3.9
License-File: LICENSE
Requires-Dist: pyyaml >=6.0
Provides-Extra: dev
Requires-Dist: black ; extra == 'dev'
Requires-Dist: pylint ; extra == 'dev'
Requires-Dist: mypy ; extra == 'dev'
Requires-Dist: types-PyYAML ; extra == 'dev'
Requires-Dist: pre-commit ; extra == 'dev'
Requires-Dist: docker ; extra == 'dev'
Requires-Dist: pytest ; extra == 'dev'
Provides-Extra: docker
Requires-Dist: docker ; extra == 'docker'
